consolemod/__init__.py
consolemod/__version__.py
consolemod/core/__init__.py
consolemod/core/core.py
consolemod/core/events.py
consolemod/core/pane.py
consolemod/input/__init__.py
consolemod/input/input.py
consolemod/input/input_handler.py
consolemod/input/keybindings.py
consolemod/interaction/__init__.py
consolemod/interaction/dialogs.py
consolemod/interaction/forms.py
consolemod/interaction/menus.py
consolemod/logging/__init__.py
consolemod/logging/logging.py
consolemod/monitoring/__init__.py
consolemod/monitoring/debounce.py
consolemod/monitoring/metrics.py
consolemod/ui/__init__.py
consolemod/ui/layout.py
consolemod/ui/themes.py
consolemod/ui/widgets.py
consolemod/utils/__init__.py
consolemod/utils/buffer.py
consolemod/utils/config.py
consolemod/utils/console.py
consolemod/utils/export.py
consolemod/utils/formatter.py
consolemod/utils/history.py
consolemod/utils/utils.py
consolemod/utils/templates/__init__.py
consolemod/utils/templates/dashboard.py
consolemod/utils/templates/logger.py
consolemod/utils/templates/monitor.py
consolemod/utils/templates/progress.py
consolemod/utils/templates/table.py
consolemod-0.2.1.dist-info/licenses/LICENSE
consolemod-0.2.1.dist-info/METADATA
consolemod-0.2.1.dist-info/WHEEL
consolemod-0.2.1.dist-info/top_level.txt
consolemod-0.2.1.dist-info/RECORD
