Metadata-Version: 2.4
Name: consolemod
Version: 0.2.1
Summary: A powerful, thread-safe terminal UI library with multi-pane support and async capabilities
Author: Conner Adams
Author-email: 404Development LLC <consolemod@404development.dev>
License: ================================================================================
Project-URL: Homepage, https://github.com/ConnerAdamsMaine/ConsoleMod
Project-URL: Documentation, https://github.com/ConnerAdamsMaine/ConsoleMod/blob/main/README.md
Project-URL: Repository, https://github.com/ConnerAdamsMaine/ConsoleMod
Project-URL: Bug Tracker, https://github.com/ConnerAdamsMaine/ConsoleMod/issues
Classifier: Development Status :: 4 - Beta
Classifier: Intended Audience :: Developers
Classifier: Programming Language :: Python :: 3.9
Classifier: Programming Language :: Python :: 3.10
Classifier: Programming Language :: Python :: 3.11
Classifier: Programming Language :: Python :: 3.12
Classifier: Programming Language :: Python :: 3.13
Requires-Python: >=3.9
License-File: LICENSE
Requires-Dist: rich>=10.0.0
Requires-Dist: readchar>=3.0.0
Provides-Extra: dev
Requires-Dist: pytest>=7.0.0; extra == "dev"
Requires-Dist: pytest-asyncio>=0.20.0; extra == "dev"
Requires-Dist: black>=22.0.0; extra == "dev"
Requires-Dist: flake8>=4.0.0; extra == "dev"
Requires-Dist: mypy>=0.950; extra == "dev"
Provides-Extra: docs
Requires-Dist: sphinx>=4.0.0; extra == "docs"
Requires-Dist: sphinx-rtd-theme>=1.0.0; extra == "docs"
Dynamic: license-file
